QtFusion/GB2312.ttf
QtFusion/LICENSE
QtFusion/LoginForm.py
QtFusion/RecSystem.py
QtFusion/__init__.py
QtFusion/setup.py
QtFusion/config/QfConfig.py
QtFusion/config/VisualConf.py
QtFusion/config/VisualSet.yaml
QtFusion/config/__init__.py
QtFusion/default_icons/__init__.py
QtFusion/handlers/Handler.py
QtFusion/handlers/__init__.py
QtFusion/manager/DetManager.py
QtFusion/manager/UserManager.py
QtFusion/manager/__init__.py
QtFusion/models/AbstractModel.py
QtFusion/models/Heatmap.py
QtFusion/models/__init__.py
QtFusion/path/FManager.py
QtFusion/path/Path.py
QtFusion/path/__init__.py
QtFusion/qss/Aqua.qss
QtFusion/qss/BlueGlass.qss
QtFusion/qss/DarkDracula.qss
QtFusion/qss/DarkGreen.qss
QtFusion/qss/DarkOrange.qss
QtFusion/qss/DarkPink.qss
QtFusion/qss/DarkPurple.qss
QtFusion/qss/DarkRed.qss
QtFusion/qss/DarkVs15.qss
QtFusion/qss/DarkYellow.qss
QtFusion/qss/ElegantDark.qss
QtFusion/qss/LightStyle.qss
QtFusion/qss/MacOS.qss
QtFusion/qss/NeonBlack.qss
QtFusion/qss/NeonButtons.qss
QtFusion/qss/NightEyes.qss
QtFusion/qss/NormDark.qss
QtFusion/qss/Parchment.qss
QtFusion/qss/Skyrim.qss
QtFusion/qss/Ubuntu.qss
QtFusion/qss/__init__.py
QtFusion/qss/style_login_white.qss
QtFusion/qss/style_main_green.qss
QtFusion/qss/style_norm_black.qss
QtFusion/qss/style_norm_white.qss
QtFusion/qss/style_trans_black.qss
QtFusion/styles/Formers.py
QtFusion/styles/Styles.py
QtFusion/styles/__init__.py
QtFusion/utils/CameraUtils.py
QtFusion/utils/DetVisual.py
QtFusion/utils/FileUtils.py
QtFusion/utils/ImageUtils.py
QtFusion/utils/Pixmap.py
QtFusion/utils/__init__.py
QtFusion/widgets/BaseFrame.py
QtFusion/widgets/ExtWidgets.py
QtFusion/widgets/SettingsDialog.py
QtFusion/widgets/TipsWidgets.py
QtFusion/widgets/Widgets.py
QtFusion/widgets/__init__.py
QtFusion-0.6.1.data/data/LICENSE
QtFusion-0.6.1.dist-info/METADATA
QtFusion-0.6.1.dist-info/WHEEL
QtFusion-0.6.1.dist-info/top_level.txt
QtFusion-0.6.1.dist-info/RECORD
